README.md
setup.cfg
setup.py
engine_grpc/__init__.py
engine_grpc/engine_pipe_abstract.py
engine_grpc/engine_pipe_channel.py
engine_grpc/engine_pipe_decorator.py
engine_grpc/engine_pipe_impl.py
engine_grpc/engine_pipe_resolver.py
engine_grpc/engine_stub_interface.py
engine_grpc/unity/__init__.py
engine_grpc/unity/engine_pipe_unity_impl.py
engine_grpc/unreal/__init__.py
engine_grpc/unreal/engine_pipe_unreal_impl.py
engine_grpc/utils/__init__.py
engine_grpc/utils/component_assemble.py
engine_grpc/utils/const_key.py
engine_grpc/utils/singleton.py
engine_grpc_pipeline.egg-info/PKG-INFO
engine_grpc_pipeline.egg-info/SOURCES.txt
engine_grpc_pipeline.egg-info/dependency_links.txt
engine_grpc_pipeline.egg-info/requires.txt
engine_grpc_pipeline.egg-info/top_level.txt