Metadata-Version: 2.1
Name: engine-grpc-pipeline
Version: 0.0.14
Summary: grpc pipeline interfaces
Home-page: https://github.com/ImagineersHub/engine-grpc-pipeline
Author: esun
Author-email: esun@voteb.com
License: MIT
Keywords: python,grpc,unity,unreal
Classifier: Development Status :: 3 - Alpha
Classifier: Programming Language :: Python :: 3.10
